ACE_calc/__init__.py
ACE_calc/__main__.py
ace_calc-0.1.0.dist-info/licenses/LICENSE
ace_calc-0.1.0.dist-info/METADATA
ace_calc-0.1.0.dist-info/WHEEL
ace_calc-0.1.0.dist-info/top_level.txt
ace_calc-0.1.0.dist-info/RECORD
