Metadata-Version: 2.4
Name: ACE-calc
Version: 0.1.0
Summary: Fast calculate the cyclone ACE.
Home-page: https://github.com/xystudio889/ACECalc
Author: xystudio
Author-email: 173288240@qq.com
License: MIT
Requires-Python: >=3.6
License-File: LICENSE
Dynamic: author
Dynamic: author-email
Dynamic: description
Dynamic: home-page
Dynamic: license
Dynamic: license-file
Dynamic: requires-python
Dynamic: summary
